edc_prn/__init__.py
edc_prn/apps.py
edc_prn/modeladmin_mixins.py
edc_prn/modelform_mixins.py
edc_prn/models.py
edc_prn/prn.py
edc_prn/site_prn_forms.py
edc_prn/templates/edc_prn/add_prn_popover.html
edc_prn/templates/edc_prn/list_prns.html
edc_prn/templatetags/__init__.py
edc_prn/templatetags/edc_prn_extras.py
edc_prn/tests/__init__.py
edc_prn/tests/helper.py
edc_prn/tests/holidays.csv
edc_prn/tests/test_settings.py
edc_prn/tests/urls.py
edc_prn/tests/etc/user-aes-local.key
edc_prn/tests/etc/user-aes-restricted.key
edc_prn/tests/etc/user-rsa-local-private.pem
edc_prn/tests/etc/user-rsa-local-public.pem
edc_prn/tests/etc/user-rsa-restricted-private.pem
edc_prn/tests/etc/user-rsa-restricted-public.pem
edc_prn/tests/etc/user-salt-local.key
edc_prn/tests/etc/user-salt-restricted.key
edc_prn/tests/tests/__init__.py
edc_prn/tests/tests/test_prn.py
edc_prn/tests/tests/test_prn_form_validator.py
edc_prn-1.1.1.dist-info/licenses/AUTHORS.rst
edc_prn-1.1.1.dist-info/licenses/LICENSE
prn_app/__init__.py
prn_app/admin.py
prn_app/apps.py
prn_app/consents.py
prn_app/models.py
prn_app/visit_schedule.py
edc_prn-1.1.1.dist-info/METADATA
edc_prn-1.1.1.dist-info/WHEEL
edc_prn-1.1.1.dist-info/top_level.txt
edc_prn-1.1.1.dist-info/RECORD
