Metadata-Version: 2.4
Name: edc-prn
Version: 1.1.1
Summary: classes and utils for PRN forms in the clinicedc/edc projects
Home-page: https://github.com/clinicedc/edc-prn
Author: Erik van Widenfelt
Author-email: ew2789@gmail.com
License: GPL license, see LICENSE
Keywords: django Edc PRN forms,clinicedc,clinical trials
Classifier: Environment :: Web Environment
Classifier: Framework :: Django
Classifier: Framework :: Django :: 5.2
Classifier: Intended Audience :: Developers
Classifier: Intended Audience :: Science/Research
Classifier: Operating System :: OS Independent
Classifier: Programming Language :: Python :: 3.12
Classifier: Programming Language :: Python :: 3.13
Classifier: License :: OSI Approved :: GNU General Public License v3 (GPLv3)
Requires-Python: >=3.12
License-File: LICENSE
License-File: AUTHORS.rst
Dynamic: license-file
